LICENSE
README.md
requirements.txt
riga.py
setup.py
riga.egg-info/PKG-INFO
riga.egg-info/SOURCES.txt
riga.egg-info/dependency_links.txt
riga.egg-info/not-zip-safe
riga.egg-info/top_level.txt